setup.py
./__init__.py
./constants.py
./corpus.py
qurancorpus.egg-info/PKG-INFO
qurancorpus.egg-info/SOURCES.txt
qurancorpus.egg-info/dependency_links.txt
qurancorpus.egg-info/not-zip-safe
qurancorpus.egg-info/requires.txt
qurancorpus.egg-info/top_level.txt